langchain_snowflake_vectorstore/__init__.py
langchain_snowflake_vectorstore/vectorstores.py
langchain_snowflake_vectorstore-0.1.0.dist-info/LICENSE
langchain_snowflake_vectorstore-0.1.0.dist-info/METADATA
langchain_snowflake_vectorstore-0.1.0.dist-info/WHEEL
langchain_snowflake_vectorstore-0.1.0.dist-info/RECORD
