Metadata-Version: 2.3
Name: langchain-snowflake-vectorstore
Version: 0.1.0
Summary: LangChain integration for Snowflake vector store
License: MIT
Author: Mark Boos
Author-email: mboos04@gmail.com
Requires-Python: >=3.9,<4.0
Classifier: License :: OSI Approved :: MIT License
Classifier: Programming Language :: Python :: 3
Classifier: Programming Language :: Python :: 3.9
Classifier: Programming Language :: Python :: 3.10
Classifier: Programming Language :: Python :: 3.11
Classifier: Programming Language :: Python :: 3.12
Classifier: Programming Language :: Python :: 3.13
Requires-Dist: langchain-core (>=0.3.0,<0.4.0)
Requires-Dist: snowflake-connector-python (>=3.0.0,<4.0.0)
Requires-Dist: snowflake-sqlalchemy (>=1.5.0,<2.0.0)
Requires-Dist: sqlalchemy (>=2.0.0,<3.0.0)
